gupload/__init__.py
gupload/__main__.py
gupload-1.1.0.dist-info/LICENSE
gupload-1.1.0.dist-info/METADATA
gupload-1.1.0.dist-info/WHEEL
gupload-1.1.0.dist-info/entry_points.txt
gupload-1.1.0.dist-info/top_level.txt
gupload-1.1.0.dist-info/RECORD
