Metadata-Version: 2.1
Name: gupload
Version: 1.1.0
Summary: Google Drive CLI Uploader
Home-page: https://github.com/hardwario/gupload
Author: HARDWARIO s.r.o.
Author-email: ask@hardwario.com
License: MIT
Keywords: gdrive python cli uploader ci
Platform: any
Classifier: Development Status :: 5 - Production/Stable
Classifier: Environment :: Console
Classifier: Intended Audience :: Developers
Classifier: License :: OSI Approved :: MIT License
Classifier: Natural Language :: English
Classifier: Operating System :: OS Independent
Classifier: Programming Language :: Python :: 3
Classifier: Topic :: Utilities
Requires-Dist: click (==7.0)
Requires-Dist: google-api-python-client (==1.7.10)
